numpy_datasets/FSDKaggle2018.py
numpy_datasets/TUTacousticscenes2017.py
numpy_datasets/__init__.py
numpy_datasets/_version.py
numpy_datasets/audiomnist.py
numpy_datasets/birdvox_70k.py
numpy_datasets/birdvox_dcase_20k.py
numpy_datasets/brain_mnist.py
numpy_datasets/cars196.py
numpy_datasets/cassava.py
numpy_datasets/celeb.py
numpy_datasets/cifar10.py
numpy_datasets/cifar100.py
numpy_datasets/cub200.py
numpy_datasets/dcase_2019_task4.py
numpy_datasets/dclde.py
numpy_datasets/dsprites.py
numpy_datasets/emnist.py
numpy_datasets/esc.py
numpy_datasets/fashionmnist.py
numpy_datasets/freefield1010.py
numpy_datasets/groove_MIDI.py
numpy_datasets/gtzan.py
numpy_datasets/high_gamma.py
numpy_datasets/ibeans.py
numpy_datasets/imagenet.py
numpy_datasets/imagenette.py
numpy_datasets/irmas.py
numpy_datasets/mini.py
numpy_datasets/mnist.py
numpy_datasets/patch_camelyon.py
numpy_datasets/picidae.py
numpy_datasets/places365_small.py
numpy_datasets/preprocess.py
numpy_datasets/rock_paper_scissors.py
numpy_datasets/seizures_neonatal.py
numpy_datasets/sonycust.py
numpy_datasets/speech_commands.py
numpy_datasets/stl10.py
numpy_datasets/svhn.py
numpy_datasets/tinyimagenet.py
numpy_datasets/univariate_timeseries.py
numpy_datasets/utils.py
numpy_datasets/vocalset.py
numpy_datasets/warblr.py
numpy_datasets/wavfile.py
numpy_datasets-0.0.2.dist-info/LICENSE
numpy_datasets-0.0.2.dist-info/METADATA
numpy_datasets-0.0.2.dist-info/WHEEL
numpy_datasets-0.0.2.dist-info/top_level.txt
numpy_datasets-0.0.2.dist-info/RECORD
