Metadata-Version: 2.1
Name: numpy-datasets
Version: 0.0.2
Summary: Datasets downloading/batching/processing in Numpy
Home-page: https://github.com/RandallBalestriero/numpy-datasets.git
Author: Randall Balestriero
Author-email: randallbalestriero@gmail.com
License: Apache-2.0
Platform: UNKNOWN
Classifier: Natural Language :: English
Classifier: Development Status :: 3 - Alpha
Classifier: Programming Language :: Python :: 3
Classifier: Operating System :: Unix
Requires-Python: >=3.6
Requires-Dist: numpy
Requires-Dist: scipy
